{
  "meta": {
    "build": {
      "build-date": "2024-07-12",
      "codified-date": "2024-06-02",
      "platform": {
        "reproducible": "false",
        "version": "2.14.0"
      },
      "repositories": [
        {
          "commit": "c55ce87e4734e50bfa61856d2559a0110c26533e",
          "name": "srmt-nsn/law-xml"
        },
        {
          "commit": "33c1bd5bad13dbf6df5b70e9c968b1c849e512ff",
          "name": "srmt-nsn/law-xml-codified-preview"
        }
      ]
    },
    "canonical-urls": {
      "html": "",
      "html-bulk": "https://github.com/srmt-nsn/law-html",
      "static-assets": "https://github.com/srmt-nsn/law-static-assets",
      "xml-bulk": "https://github.com/srmt-nsn/law-xml"
    },
    "contact": {
      "email": "help@openlawlib.org"
    },
    "description": ""
  }
}